vspider/__init__.py
vspider/test.py
vspider/vspider.py
vspider-0.0.9.dist-info/DESCRIPTION.rst
vspider-0.0.9.dist-info/METADATA
vspider-0.0.9.dist-info/RECORD
vspider-0.0.9.dist-info/WHEEL
vspider-0.0.9.dist-info/metadata.json
vspider-0.0.9.dist-info/top_level.txt
