Metadata-Version: 2.0
Name: vspider
Version: 0.0.9
Summary: minimalist crawling framework.
Home-page: https://github.com/cilame/vspider
Author: vilame
Author-email: opaquism@hotmail.com
License: MIT
Platform: UNKNOWN
Classifier: Environment :: Web Environment
Classifier: Intended Audience :: Developers
Classifier: Operating System :: OS Independent
